<?xml version="1.0" encoding="UTF-8" ?>
<!DOCTYPE mapper PUBLIC "-//mybatis.org//DTD Mapper 3.0//EN" "http://mybatis.org/dtd/mybatis-3-mapper.dtd" >
<mapper namespace="cn.hsa.module.insure.emr.dao.InsureEmrDieinfoDAO" >
  <resultMap id="BaseResultMap" type="cn.hsa.module.insure.emr.entity.InsureEmrDieinfoDO" >
    <!--
      WARNING - @mbggenerated
      This element is automatically generated by MyBatis Generator, do not modify.
    -->
    <result column="uuid" property="uuid" jdbcType="BIGINT" />
    <result column="org_uuid" property="orgUuid" jdbcType="BIGINT" />
    <result column="mdtrt_sn" property="mdtrtSn" jdbcType="VARCHAR" />
    <result column="mdtrt_id" property="mdtrtId" jdbcType="VARCHAR" />
    <result column="psn_no" property="psnNo" jdbcType="VARCHAR" />
    <result column="dept" property="dept" jdbcType="VARCHAR" />
    <result column="dept_name" property="deptName" jdbcType="VARCHAR" />
    <result column="wardarea_name" property="wardareaName" jdbcType="VARCHAR" />
    <result column="bedno" property="bedno" jdbcType="VARCHAR" />
    <result column="adm_time" property="admTime" jdbcType="TIMESTAMP" />
    <result column="adm_dise" property="admDise" jdbcType="VARCHAR" />
    <result column="adm_info" property="admInfo" jdbcType="VARCHAR" />
    <result column="trt_proc_dscr" property="trtProcDscr" jdbcType="VARCHAR" />
    <result column="die_time" property="dieTime" jdbcType="TIMESTAMP" />
    <result column="die_drt_rea" property="dieDrtRea" jdbcType="VARCHAR" />
    <result column="die_drt_rea_code" property="dieDrtReaCode" jdbcType="VARCHAR" />
    <result column="die_dise_name" property="dieDiseName" jdbcType="VARCHAR" />
    <result column="die_diag_code" property="dieDiagCode" jdbcType="VARCHAR" />
    <result column="agre_corp_dset" property="agreCorpDset" jdbcType="VARCHAR" />
    <result column="ipdr_name" property="ipdrName" jdbcType="VARCHAR" />
    <result column="chfpdr_code" property="chfpdrCode" jdbcType="VARCHAR" />
    <result column="chfpdr_name" property="chfpdrName" jdbcType="VARCHAR" />
    <result column="chfdr_name" property="chfdrName" jdbcType="VARCHAR" />
    <result column="sign_time" property="signTime" jdbcType="VARCHAR" />
    <result column="vali_flag" property="valiFlag" jdbcType="VARCHAR" />
    <result column="source" property="source" jdbcType="VARCHAR" />
    <result column="create_time" property="createTime" jdbcType="TIMESTAMP" />
    <result column="update_time" property="updateTime" jdbcType="TIMESTAMP" />
    <result column="hosp_code" property="hospCode" jdbcType="VARCHAR" />
  </resultMap>
  <sql id="Example_Where_Clause" >
    <!--
      WARNING - @mbggenerated
      This element is automatically generated by MyBatis Generator, do not modify.
    -->
    <where >
      <foreach collection="oredCriteria" item="criteria" separator="or" >
        <if test="criteria.valid" >
          <trim prefix="(" suffix=")" prefixOverrides="and" >
            <foreach collection="criteria.criteria" item="criterion" >
              <choose >
                <when test="criterion.noValue" >
                  and ${criterion.condition}
                </when>
                <when test="criterion.singleValue" >
                  and ${criterion.condition} #{criterion.value}
                </when>
                <when test="criterion.betweenValue" >
                  and ${criterion.condition} #{criterion.value} and #{criterion.secondValue}
                </when>
                <when test="criterion.listValue" >
                  and ${criterion.condition}
                  <foreach collection="criterion.value" item="listItem" open="(" close=")" separator="," >
                    #{listItem}
                  </foreach>
                </when>
              </choose>
            </foreach>
          </trim>
        </if>
      </foreach>
    </where>
  </sql>
  <sql id="Update_By_Example_Where_Clause" >
    <!--
      WARNING - @mbggenerated
      This element is automatically generated by MyBatis Generator, do not modify.
    -->
    <where >
      <foreach collection="example.oredCriteria" item="criteria" separator="or" >
        <if test="criteria.valid" >
          <trim prefix="(" suffix=")" prefixOverrides="and" >
            <foreach collection="criteria.criteria" item="criterion" >
              <choose >
                <when test="criterion.noValue" >
                  and ${criterion.condition}
                </when>
                <when test="criterion.singleValue" >
                  and ${criterion.condition} #{criterion.value}
                </when>
                <when test="criterion.betweenValue" >
                  and ${criterion.condition} #{criterion.value} and #{criterion.secondValue}
                </when>
                <when test="criterion.listValue" >
                  and ${criterion.condition}
                  <foreach collection="criterion.value" item="listItem" open="(" close=")" separator="," >
                    #{listItem}
                  </foreach>
                </when>
              </choose>
            </foreach>
          </trim>
        </if>
      </foreach>
    </where>
  </sql>
  <sql id="Base_Column_List" >
    <!--
      WARNING - @mbggenerated
      This element is automatically generated by MyBatis Generator, do not modify.
    -->
    uuid, org_uuid, mdtrt_sn, mdtrt_id, psn_no, dept, dept_name, wardarea_name, bedno, 
    adm_time, adm_dise, adm_info, trt_proc_dscr, die_time, die_drt_rea, die_drt_rea_code, 
    die_dise_name, die_diag_code, agre_corp_dset, ipdr_name, chfpdr_code, chfpdr_name, 
    chfdr_name, sign_time, vali_flag, source, create_time, update_time, hosp_code
  </sql>

  <select id="queryByMdtrtSn" resultType="cn.hsa.module.insure.emr.dto.InsureEmrDieinfoDTO">
    SELECT <include refid="Base_Column_List"/>
    FROM insure_emr_dieinfo
    where mdtrt_sn = #{mdtrtSn} and mdtrt_id = #{mdtrtId} and vali_flag = '1'
  </select>

    <select id="queryInfoByMdtrtSn" resultType="cn.hsa.module.insure.emr.dto.InsureEmrDieinfoDTO">
        SELECT <include refid="Base_Column_List"/>
        FROM insure_emr_dieinfo
        where mdtrt_sn = #{mdtrtSn} and vali_flag = '1'
    </select>

    <select id="queryByUuid" resultType="cn.hsa.module.insure.emr.dto.InsureEmrDieinfoDTO">
        SELECT <include refid="Base_Column_List"/>
        FROM insure_emr_dieinfo
        where uuid = #{uuid}
    </select>

  <select id="select" resultMap="BaseResultMap" parameterType="cn.hsa.module.insure.emr.entity.InsureEmrDieinfoDO" >
    <!--
      WARNING - @mbggenerated
      This element is automatically generated by MyBatis Generator, do not modify.
    -->
    select
    <if test="distinct" >
      distinct
    </if>
    <include refid="Base_Column_List" />
    from insure_emr_dieinfo
    <if test="_parameter != null" >
      <include refid="Example_Where_Clause" />
    </if>
    <if test="orderByClause != null" >
      order by ${orderByClause}
    </if>
  </select>
  <delete id="delete" parameterType="cn.hsa.module.insure.emr.entity.InsureEmrDieinfoDO" >
    <!--
      WARNING - @mbggenerated
      This element is automatically generated by MyBatis Generator, do not modify.
    -->
    delete from insure_emr_dieinfo
    <if test="_parameter != null" >
      <include refid="Example_Where_Clause" />
    </if>
  </delete>
  <insert id="insert" parameterType="cn.hsa.module.insure.emr.entity.InsureEmrDieinfoDO" >
    <!--
      WARNING - @mbggenerated
      This element is automatically generated by MyBatis Generator, do not modify.
    -->
    insert into insure_emr_dieinfo (uuid, org_uuid, mdtrt_sn, 
      mdtrt_id, psn_no, dept, 
      dept_name, wardarea_name, bedno, 
      adm_time, adm_dise, adm_info, 
      trt_proc_dscr, die_time, die_drt_rea, 
      die_drt_rea_code, die_dise_name, die_diag_code, 
      agre_corp_dset, ipdr_name, chfpdr_code, 
      chfpdr_name, chfdr_name, sign_time, 
      vali_flag, source, create_time, 
      update_time, hosp_code, emr_template_id)
    values (#{uuid,jdbcType=BIGINT}, #{orgUuid,jdbcType=BIGINT}, #{mdtrtSn,jdbcType=VARCHAR}, 
      #{mdtrtId,jdbcType=VARCHAR}, #{psnNo,jdbcType=VARCHAR}, #{dept,jdbcType=VARCHAR}, 
      #{deptName,jdbcType=VARCHAR}, #{wardareaName,jdbcType=VARCHAR}, #{bedno,jdbcType=VARCHAR}, 
      #{admTime,jdbcType=TIMESTAMP}, #{admDise,jdbcType=VARCHAR}, #{admInfo,jdbcType=VARCHAR}, 
      #{trtProcDscr,jdbcType=VARCHAR}, #{dieTime,jdbcType=TIMESTAMP}, #{dieDrtRea,jdbcType=VARCHAR}, 
      #{dieDrtReaCode,jdbcType=VARCHAR}, #{dieDiseName,jdbcType=VARCHAR}, #{dieDiagCode,jdbcType=VARCHAR}, 
      #{agreCorpDset,jdbcType=VARCHAR}, #{ipdrName,jdbcType=VARCHAR}, #{chfpdrCode,jdbcType=VARCHAR}, 
      #{chfpdrName,jdbcType=VARCHAR}, #{chfdrName,jdbcType=VARCHAR}, #{signTime,jdbcType=VARCHAR}, 
      #{valiFlag,jdbcType=VARCHAR}, #{source,jdbcType=VARCHAR}, #{createTime,jdbcType=TIMESTAMP}, 
      #{updateTime,jdbcType=TIMESTAMP}, #{hospCode,jdbcType=VARCHAR},#{emrTemplateId,jdbcType=VARCHAR})
  </insert>
  <insert id="insertSelective" parameterType="cn.hsa.module.insure.emr.entity.InsureEmrDieinfoDO" >
    <!--
      WARNING - @mbggenerated
      This element is automatically generated by MyBatis Generator, do not modify.
    -->
    insert into insure_emr_dieinfo
    <trim prefix="(" suffix=")" suffixOverrides="," >
      <if test="uuid != null" >
        uuid,
      </if>
      <if test="orgUuid != null" >
        org_uuid,
      </if>
      <if test="mdtrtSn != null" >
        mdtrt_sn,
      </if>
      <if test="mdtrtId != null" >
        mdtrt_id,
      </if>
      <if test="psnNo != null" >
        psn_no,
      </if>
      <if test="dept != null" >
        dept,
      </if>
      <if test="deptName != null" >
        dept_name,
      </if>
      <if test="wardareaName != null" >
        wardarea_name,
      </if>
      <if test="bedno != null" >
        bedno,
      </if>
      <if test="admTime != null" >
        adm_time,
      </if>
      <if test="admDise != null" >
        adm_dise,
      </if>
      <if test="admInfo != null" >
        adm_info,
      </if>
      <if test="trtProcDscr != null" >
        trt_proc_dscr,
      </if>
      <if test="dieTime != null" >
        die_time,
      </if>
      <if test="dieDrtRea != null" >
        die_drt_rea,
      </if>
      <if test="dieDrtReaCode != null" >
        die_drt_rea_code,
      </if>
      <if test="dieDiseName != null" >
        die_dise_name,
      </if>
      <if test="dieDiagCode != null" >
        die_diag_code,
      </if>
      <if test="agreCorpDset != null" >
        agre_corp_dset,
      </if>
      <if test="ipdrName != null" >
        ipdr_name,
      </if>
      <if test="chfpdrCode != null" >
        chfpdr_code,
      </if>
      <if test="chfpdrName != null" >
        chfpdr_name,
      </if>
      <if test="chfdrName != null" >
        chfdr_name,
      </if>
      <if test="signTime != null" >
        sign_time,
      </if>
      <if test="valiFlag != null" >
        vali_flag,
      </if>
      <if test="source != null" >
        source,
      </if>
      <if test="createTime != null" >
        create_time,
      </if>
      <if test="updateTime != null" >
        update_time,
      </if>
      <if test="hospCode != null" >
        hosp_code,
      </if>
    </trim>
    <trim prefix="values (" suffix=")" suffixOverrides="," >
      <if test="uuid != null" >
        #{uuid,jdbcType=BIGINT},
      </if>
      <if test="orgUuid != null" >
        #{orgUuid,jdbcType=BIGINT},
      </if>
      <if test="mdtrtSn != null" >
        #{mdtrtSn,jdbcType=VARCHAR},
      </if>
      <if test="mdtrtId != null" >
        #{mdtrtId,jdbcType=VARCHAR},
      </if>
      <if test="psnNo != null" >
        #{psnNo,jdbcType=VARCHAR},
      </if>
      <if test="dept != null" >
        #{dept,jdbcType=VARCHAR},
      </if>
      <if test="deptName != null" >
        #{deptName,jdbcType=VARCHAR},
      </if>
      <if test="wardareaName != null" >
        #{wardareaName,jdbcType=VARCHAR},
      </if>
      <if test="bedno != null" >
        #{bedno,jdbcType=VARCHAR},
      </if>
      <if test="admTime != null" >
        #{admTime,jdbcType=TIMESTAMP},
      </if>
      <if test="admDise != null" >
        #{admDise,jdbcType=VARCHAR},
      </if>
      <if test="admInfo != null" >
        #{admInfo,jdbcType=VARCHAR},
      </if>
      <if test="trtProcDscr != null" >
        #{trtProcDscr,jdbcType=VARCHAR},
      </if>
      <if test="dieTime != null" >
        #{dieTime,jdbcType=TIMESTAMP},
      </if>
      <if test="dieDrtRea != null" >
        #{dieDrtRea,jdbcType=VARCHAR},
      </if>
      <if test="dieDrtReaCode != null" >
        #{dieDrtReaCode,jdbcType=VARCHAR},
      </if>
      <if test="dieDiseName != null" >
        #{dieDiseName,jdbcType=VARCHAR},
      </if>
      <if test="dieDiagCode != null" >
        #{dieDiagCode,jdbcType=VARCHAR},
      </if>
      <if test="agreCorpDset != null" >
        #{agreCorpDset,jdbcType=VARCHAR},
      </if>
      <if test="ipdrName != null" >
        #{ipdrName,jdbcType=VARCHAR},
      </if>
      <if test="chfpdrCode != null" >
        #{chfpdrCode,jdbcType=VARCHAR},
      </if>
      <if test="chfpdrName != null" >
        #{chfpdrName,jdbcType=VARCHAR},
      </if>
      <if test="chfdrName != null" >
        #{chfdrName,jdbcType=VARCHAR},
      </if>
      <if test="signTime != null" >
        #{signTime,jdbcType=VARCHAR},
      </if>
      <if test="valiFlag != null" >
        #{valiFlag,jdbcType=VARCHAR},
      </if>
      <if test="source != null" >
        #{source,jdbcType=VARCHAR},
      </if>
      <if test="createTime != null" >
        #{createTime,jdbcType=TIMESTAMP},
      </if>
      <if test="updateTime != null" >
        #{updateTime,jdbcType=TIMESTAMP},
      </if>
      <if test="hospCode != null" >
        #{hospCode,jdbcType=VARCHAR},
      </if>
    </trim>
  </insert>
  <select id="countByExample" parameterType="cn.hsa.module.insure.emr.entity.InsureEmrDieinfoDO" resultType="java.lang.Integer" >
    <!--
      WARNING - @mbggenerated
      This element is automatically generated by MyBatis Generator, do not modify.
    -->
    select count(*) from insure_emr_dieinfo
    <if test="_parameter != null" >
      <include refid="Example_Where_Clause" />
    </if>
  </select>
  <update id="updateSelective" parameterType="map" >
    <!--
      WARNING - @mbggenerated
      This element is automatically generated by MyBatis Generator, do not modify.
    -->
    update insure_emr_dieinfo
    <set >
      <if test="uuid != null" >
        uuid = #{uuid,jdbcType=BIGINT},
      </if>
      <if test="orgUuid != null" >
        org_uuid = #{orgUuid,jdbcType=BIGINT},
      </if>
      <if test="mdtrtSn != null" >
        mdtrt_sn = #{mdtrtSn,jdbcType=VARCHAR},
      </if>
      <if test="mdtrtId != null" >
        mdtrt_id = #{mdtrtId,jdbcType=VARCHAR},
      </if>
      <if test="psnNo != null" >
        psn_no = #{psnNo,jdbcType=VARCHAR},
      </if>
      <if test="dept != null" >
        dept = #{dept,jdbcType=VARCHAR},
      </if>
      <if test="deptName != null" >
        dept_name = #{deptName,jdbcType=VARCHAR},
      </if>
      <if test="wardareaName != null" >
        wardarea_name = #{wardareaName,jdbcType=VARCHAR},
      </if>
      <if test="bedno != null" >
        bedno = #{bedno,jdbcType=VARCHAR},
      </if>
      <if test="admTime != null" >
        adm_time = #{admTime,jdbcType=TIMESTAMP},
      </if>
      <if test="admDise != null" >
        adm_dise = #{admDise,jdbcType=VARCHAR},
      </if>
      <if test="admInfo != null" >
        adm_info = #{admInfo,jdbcType=VARCHAR},
      </if>
      <if test="trtProcDscr != null" >
        trt_proc_dscr = #{trtProcDscr,jdbcType=VARCHAR},
      </if>
      <if test="dieTime != null" >
        die_time = #{dieTime,jdbcType=TIMESTAMP},
      </if>
      <if test="dieDrtRea != null" >
        die_drt_rea = #{dieDrtRea,jdbcType=VARCHAR},
      </if>
      <if test="dieDrtReaCode != null" >
        die_drt_rea_code = #{dieDrtReaCode,jdbcType=VARCHAR},
      </if>
      <if test="dieDiseName != null" >
        die_dise_name = #{dieDiseName,jdbcType=VARCHAR},
      </if>
      <if test="dieDiagCode != null" >
        die_diag_code = #{dieDiagCode,jdbcType=VARCHAR},
      </if>
      <if test="agreCorpDset != null" >
        agre_corp_dset = #{agreCorpDset,jdbcType=VARCHAR},
      </if>
      <if test="ipdrName != null" >
        ipdr_name = #{ipdrName,jdbcType=VARCHAR},
      </if>
      <if test="chfpdrCode != null" >
        chfpdr_code = #{chfpdrCode,jdbcType=VARCHAR},
      </if>
      <if test="chfpdrName != null" >
        chfpdr_name = #{chfpdrName,jdbcType=VARCHAR},
      </if>
      <if test="chfdrName != null" >
        chfdr_name = #{chfdrName,jdbcType=VARCHAR},
      </if>
      <if test="signTime != null" >
        sign_time = #{signTime,jdbcType=VARCHAR},
      </if>
      <if test="valiFlag != null" >
        vali_flag = #{valiFlag,jdbcType=VARCHAR},
      </if>
      <if test="source != null" >
        source = #{source,jdbcType=VARCHAR},
      </if>
      <if test="createTime != null" >
        create_time = #{createTime,jdbcType=TIMESTAMP},
      </if>
      <if test="updateTime != null" >
        update_time = #{updateTime,jdbcType=TIMESTAMP},
      </if>
      <if test="hospCode != null" >
        hosp_code = #{hospCode,jdbcType=VARCHAR},
      </if>
    </set>
    where uuid = #{uuid}
  </update>

    <update id="updateDieSelective" parameterType="map" >
        <!--
          WARNING - @mbggenerated
          This element is automatically generated by MyBatis Generator, do not modify.
        -->
        update insure_emr_dieinfo
        <set >
            <if test="uuid != null" >
                uuid = #{uuid,jdbcType=BIGINT},
            </if>
            <if test="orgUuid != null" >
                org_uuid = #{orgUuid,jdbcType=BIGINT},
            </if>
            <if test="mdtrtSn != null" >
                mdtrt_sn = #{mdtrtSn,jdbcType=VARCHAR},
            </if>
            <if test="mdtrtId != null" >
                mdtrt_id = #{mdtrtId,jdbcType=VARCHAR},
            </if>
            <if test="psnNo != null" >
                psn_no = #{psnNo,jdbcType=VARCHAR},
            </if>
            <if test="dept != null" >
                dept = #{dept,jdbcType=VARCHAR},
            </if>
            <if test="deptName != null" >
                dept_name = #{deptName,jdbcType=VARCHAR},
            </if>
            <if test="wardareaName != null" >
                wardarea_name = #{wardareaName,jdbcType=VARCHAR},
            </if>
            <if test="bedno != null" >
                bedno = #{bedno,jdbcType=VARCHAR},
            </if>
            <if test="admTime != null" >
                adm_time = #{admTime,jdbcType=TIMESTAMP},
            </if>
            <if test="admDise != null" >
                adm_dise = #{admDise,jdbcType=VARCHAR},
            </if>
            <if test="admInfo != null" >
                adm_info = #{admInfo,jdbcType=VARCHAR},
            </if>
            <if test="trtProcDscr != null" >
                trt_proc_dscr = #{trtProcDscr,jdbcType=VARCHAR},
            </if>
            <if test="dieTime != null" >
                die_time = #{dieTime,jdbcType=TIMESTAMP},
            </if>
            <if test="dieDrtRea != null" >
                die_drt_rea = #{dieDrtRea,jdbcType=VARCHAR},
            </if>
            <if test="dieDrtReaCode != null" >
                die_drt_rea_code = #{dieDrtReaCode,jdbcType=VARCHAR},
            </if>
            <if test="dieDiseName != null" >
                die_dise_name = #{dieDiseName,jdbcType=VARCHAR},
            </if>
            <if test="dieDiagCode != null" >
                die_diag_code = #{dieDiagCode,jdbcType=VARCHAR},
            </if>
            <if test="agreCorpDset != null" >
                agre_corp_dset = #{agreCorpDset,jdbcType=VARCHAR},
            </if>
            <if test="ipdrName != null" >
                ipdr_name = #{ipdrName,jdbcType=VARCHAR},
            </if>
            <if test="chfpdrCode != null" >
                chfpdr_code = #{chfpdrCode,jdbcType=VARCHAR},
            </if>
            <if test="chfpdrName != null" >
                chfpdr_name = #{chfpdrName,jdbcType=VARCHAR},
            </if>
            <if test="chfdrName != null" >
                chfdr_name = #{chfdrName,jdbcType=VARCHAR},
            </if>
            <if test="signTime != null" >
                sign_time = #{signTime,jdbcType=VARCHAR},
            </if>
            <if test="valiFlag != null" >
                vali_flag = #{valiFlag,jdbcType=VARCHAR},
            </if>
            <if test="source != null" >
                source = #{source,jdbcType=VARCHAR},
            </if>
            <if test="createTime != null" >
                create_time = #{createTime,jdbcType=TIMESTAMP},
            </if>
            <if test="updateTime != null" >
                update_time = #{updateTime,jdbcType=TIMESTAMP},
            </if>
            <if test="hospCode != null" >
                hosp_code = #{hospCode,jdbcType=VARCHAR},
            </if>
        </set>
        where mdtrt_sn = #{visitId}
    </update>

  <update id="updateByExample" parameterType="map" >
    <!--
      WARNING - @mbggenerated
      This element is automatically generated by MyBatis Generator, do not modify.
    -->
    update insure_emr_dieinfo
    set uuid = #{record.uuid,jdbcType=BIGINT},
      org_uuid = #{record.orgUuid,jdbcType=BIGINT},
      mdtrt_sn = #{record.mdtrtSn,jdbcType=VARCHAR},
      mdtrt_id = #{record.mdtrtId,jdbcType=VARCHAR},
      psn_no = #{record.psnNo,jdbcType=VARCHAR},
      dept = #{record.dept,jdbcType=VARCHAR},
      dept_name = #{record.deptName,jdbcType=VARCHAR},
      wardarea_name = #{record.wardareaName,jdbcType=VARCHAR},
      bedno = #{record.bedno,jdbcType=VARCHAR},
      adm_time = #{record.admTime,jdbcType=TIMESTAMP},
      adm_dise = #{record.admDise,jdbcType=VARCHAR},
      adm_info = #{record.admInfo,jdbcType=VARCHAR},
      trt_proc_dscr = #{record.trtProcDscr,jdbcType=VARCHAR},
      die_time = #{record.dieTime,jdbcType=TIMESTAMP},
      die_drt_rea = #{record.dieDrtRea,jdbcType=VARCHAR},
      die_drt_rea_code = #{record.dieDrtReaCode,jdbcType=VARCHAR},
      die_dise_name = #{record.dieDiseName,jdbcType=VARCHAR},
      die_diag_code = #{record.dieDiagCode,jdbcType=VARCHAR},
      agre_corp_dset = #{record.agreCorpDset,jdbcType=VARCHAR},
      ipdr_name = #{record.ipdrName,jdbcType=VARCHAR},
      chfpdr_code = #{record.chfpdrCode,jdbcType=VARCHAR},
      chfpdr_name = #{record.chfpdrName,jdbcType=VARCHAR},
      chfdr_name = #{record.chfdrName,jdbcType=VARCHAR},
      sign_time = #{record.signTime,jdbcType=VARCHAR},
      vali_flag = #{record.valiFlag,jdbcType=VARCHAR},
      source = #{record.source,jdbcType=VARCHAR},
      create_time = #{record.createTime,jdbcType=TIMESTAMP},
      update_time = #{record.updateTime,jdbcType=TIMESTAMP},
      hosp_code = #{record.hospCode,jdbcType=VARCHAR}
    <if test="_parameter != null" >
      <include refid="Update_By_Example_Where_Clause" />
    </if>
  </update>

  <delete id="deleteByMap" parameterType="map" >
    <!--
      WARNING - @mbggenerated
      This element is automatically generated by MyBatis Generator, do not modify.
    -->
    delete from insure_emr_dieinfo
    <if test="_parameter != null" >
      <include refid="Example_Where_Clause" />
    </if>
  </delete>

  <insert id="insertList" parameterType="list" >
    <!--
      WARNING - @mbggenerated
      This element is automatically generated by MyBatis Generator, do not modify.
    -->
    insert into insure_emr_dieinfo (uuid, org_uuid, mdtrt_sn,
    mdtrt_id, psn_no, dept,
    dept_name, wardarea_name, bedno,
    adm_time, adm_dise, adm_info,
    trt_proc_dscr, die_time, die_drt_rea,
    die_drt_rea_code, die_dise_name, die_diag_code,
    agre_corp_dset, ipdr_name, chfpdr_code,
    chfpdr_name, chfdr_name, sign_time,
    vali_flag, source, create_time,
    update_time, hosp_code)
    values
    <foreach collection ="list" item="item" separator =",">
      (#{item.uuid,jdbcType=BIGINT}, #{item.orgUuid,jdbcType=BIGINT}, #{item.mdtrtSn,jdbcType=VARCHAR},
      #{item.mdtrtId,jdbcType=VARCHAR}, #{item.psnNo,jdbcType=VARCHAR}, #{item.dept,jdbcType=VARCHAR},
      #{item.deptName,jdbcType=VARCHAR}, #{item.wardareaName,jdbcType=VARCHAR}, #{item.bedno,jdbcType=VARCHAR},
      #{item.admTime,jdbcType=TIMESTAMP}, #{item.admDise,jdbcType=VARCHAR}, #{item.admInfo,jdbcType=VARCHAR},
      #{item.trtProcDscr,jdbcType=VARCHAR}, #{item.dieTime,jdbcType=TIMESTAMP}, #{item.dieDrtRea,jdbcType=VARCHAR},
      #{item.dieDrtReaCode,jdbcType=VARCHAR}, #{item.dieDiseName,jdbcType=VARCHAR}, #{item.dieDiagCode,jdbcType=VARCHAR},
      #{item.agreCorpDset,jdbcType=VARCHAR}, #{item.ipdrName,jdbcType=VARCHAR}, #{item.chfpdrCode,jdbcType=VARCHAR},
      #{item.chfpdrName,jdbcType=VARCHAR}, #{item.chfdrName,jdbcType=VARCHAR}, #{item.signTime,jdbcType=VARCHAR},
      #{item.valiFlag,jdbcType=VARCHAR}, #{item.source,jdbcType=VARCHAR}, #{item.createTime,jdbcType=TIMESTAMP},
      #{item.updateTime,jdbcType=TIMESTAMP}, #{item.hospCode,jdbcType=VARCHAR})
    </foreach >

  </insert>
</mapper>